libpkuipgw/__init__.py
libpkuipgw/libpkuipgw.py
libpkuipgw-0.2.6.data/scripts/pkuipgw
libpkuipgw-0.2.6.dist-info/METADATA
libpkuipgw-0.2.6.dist-info/WHEEL
libpkuipgw-0.2.6.dist-info/top_level.txt
libpkuipgw-0.2.6.dist-info/RECORD
