Metadata-Version: 2.1
Name: libpkuipgw
Version: 0.2.6
Summary: Python library for accessing the Internet in Peking University.
Home-page: https://github.com/YibaiMeng/libpkuipgw
Author: Meng Yibai
Author-email: mengyibai@pku.edu.cn
License: MIT
Platform: UNKNOWN
Classifier: Programming Language :: Python :: 3
Classifier: License :: OSI Approved :: MIT License
Classifier: Operating System :: OS Independent
Requires-Dist: netifaces
Requires-Dist: requests
